nomodeco/__init__.py
nomodeco/libraries/__init__.py
nomodeco/libraries/arguments.py
nomodeco/libraries/bmatrix.py
nomodeco/libraries/gaussian_parser.py
nomodeco/libraries/icsel.py
nomodeco/libraries/icset_opt.py
nomodeco/libraries/icset_opt_multproc.py
nomodeco/libraries/logfile.py
nomodeco/libraries/molpro_parser.py
nomodeco/libraries/nomodeco_classes.py
nomodeco/libraries/orca_parser.py
nomodeco/libraries/specifications.py
nomodeco/libraries/test_modules/coord_transf.py
nomodeco/libraries/test_modules/degofc.py
nomodeco/libraries/topology.py
nomodeco/nomodeco.py
nomodeco-0.2.6.dist-info/LICENSE
nomodeco-0.2.6.dist-info/METADATA
nomodeco-0.2.6.dist-info/WHEEL
nomodeco-0.2.6.dist-info/entry_points.txt
nomodeco-0.2.6.dist-info/RECORD
