Metadata-Version: 2.1
Name: nomodeco
Version: 0.2.6
Summary: a python package for the determination of optimal internal coordinate systems for molecular structures
Home-page: https://github.com/KemalOenen/decomposing-vibrations
Keywords: internal coordinates,quantum chemistry
Author: KemalÖnen
Requires-Python: >=3.12.5,<3.13
Classifier: Programming Language :: Python :: 3
Requires-Dist: ase (>=3.23.0,<4.0.0)
Requires-Dist: inquirer (>=3.4.0,<4.0.0)
Requires-Dist: matplotlib (>=3.9.2,<4.0.0)
Requires-Dist: mendeleev (>=0.17.0,<0.18.0)
Requires-Dist: networkx (>=3.3,<4.0)
Requires-Dist: numpy (>=1.26.4,<2.0.0)
Requires-Dist: pandas (>=2.2.2,<3.0.0)
Requires-Dist: pubchempy (>=1.0.4,<2.0.0)
Requires-Dist: pyfiglet (>=0.8.post1,<0.9)
Requires-Dist: pymatgen (>=2024.9.17,<2025.0.0)
Requires-Dist: scipy (>=1.14.1,<2.0.0)
Requires-Dist: seaborn (>=0.13.2,<0.14.0)
Requires-Dist: setuptools (>=73.0.01,<74.0.0)
Project-URL: Repository, https://github.com/KemalOenen/decomposing-vibrations
